Metadata-Version: 2.4
Name: csp-gateway-client
Version: 2.4.4
Summary: csp-gateway is a framework for building high-performance streaming applications
Project-URL: Repository, https://github.com/Point72/csp-gateway
Project-URL: Homepage, https://github.com/Point72/csp-gateway/wiki
Author-email: "Point72, L.P." <OpenSource@point72.com>
License: Apache-2.0
License-File: LICENSE
Keywords: csp,csp-gateway
Classifier: Development Status :: 3 - Alpha
Classifier: Programming Language :: Python
Classifier: Programming Language :: Python :: 3
Classifier: Programming Language :: Python :: 3.10
Classifier: Programming Language :: Python :: 3.11
Classifier: Programming Language :: Python :: 3.12
Classifier: Programming Language :: Python :: 3.13
Classifier: Programming Language :: Python :: 3.14
Classifier: Programming Language :: Python :: Implementation :: CPython
Classifier: Programming Language :: Python :: Implementation :: PyPy
Requires-Python: >=3.10
Requires-Dist: httpx
Requires-Dist: jsonref
Requires-Dist: nest-asyncio
Requires-Dist: packaging
Requires-Dist: pydantic<2.12,>=2
Provides-Extra: develop
Requires-Dist: aiohttp; extra == 'develop'
Requires-Dist: aiostream; extra == 'develop'
Requires-Dist: arrow-odbc; extra == 'develop'
Requires-Dist: asv; extra == 'develop'
Requires-Dist: build; extra == 'develop'
Requires-Dist: bump-my-version; extra == 'develop'
Requires-Dist: check-manifest; extra == 'develop'
Requires-Dist: codespell<2.5,>=2.4; extra == 'develop'
Requires-Dist: datadog; extra == 'develop'
Requires-Dist: hatch-js; extra == 'develop'
Requires-Dist: hatch-multi>=1; extra == 'develop'
Requires-Dist: hatchling; extra == 'develop'
Requires-Dist: httpx; extra == 'develop'
Requires-Dist: jsonref; extra == 'develop'
Requires-Dist: mdformat-tables>=1; extra == 'develop'
Requires-Dist: mdformat<1.1,>=0.7.22; extra == 'develop'
Requires-Dist: nest-asyncio; extra == 'develop'
Requires-Dist: opsgenie-sdk; extra == 'develop'
Requires-Dist: packaging; extra == 'develop'
Requires-Dist: pandas; extra == 'develop'
Requires-Dist: polars; extra == 'develop'
Requires-Dist: pytest; extra == 'develop'
Requires-Dist: pytest-aiohttp; extra == 'develop'
Requires-Dist: pytest-asyncio; extra == 'develop'
Requires-Dist: pytest-cov; extra == 'develop'
Requires-Dist: python-magic; extra == 'develop'
Requires-Dist: ruff<0.15,>=0.9; extra == 'develop'
Requires-Dist: sqlalchemy; extra == 'develop'
Requires-Dist: twine; extra == 'develop'
Requires-Dist: watchdog; extra == 'develop'
Requires-Dist: wheel; extra == 'develop'
Provides-Extra: server
Requires-Dist: atomic-counter>=0.1.3; extra == 'server'
Requires-Dist: ccflow<1,>=0.5.9; extra == 'server'
Requires-Dist: colorlog; extra == 'server'
Requires-Dist: csp<1,>=0.8.0; extra == 'server'
Requires-Dist: deprecation; extra == 'server'
Requires-Dist: duckdb<1.4.1,>=0.10; extra == 'server'
Requires-Dist: fastapi>=0.110; extra == 'server'
Requires-Dist: fsspec; extra == 'server'
Requires-Dist: hydra-core; extra == 'server'
Requires-Dist: janus; extra == 'server'
Requires-Dist: omegaconf; extra == 'server'
Requires-Dist: orjson; extra == 'server'
Requires-Dist: perspective-python<4.1,>=4; extra == 'server'
Requires-Dist: psutil; extra == 'server'
Requires-Dist: pyarrow; extra == 'server'
Requires-Dist: pydantic<2.12,>=2; extra == 'server'
Requires-Dist: uvicorn<0.39,>=0.28.1; extra == 'server'
Requires-Dist: uvloop; extra == 'server'
Requires-Dist: websockets; extra == 'server'
